ak_pynn/__init__.py
ak_pynn/mlp.py
ak_pynn/nnv.py
ak_pynn/utils.py
ak_pynn-0.1.8.dist-info/LICENCE.md
ak_pynn-0.1.8.dist-info/METADATA
ak_pynn-0.1.8.dist-info/WHEEL
ak_pynn-0.1.8.dist-info/top_level.txt
ak_pynn-0.1.8.dist-info/RECORD
