Metadata-Version: 2.1
Name: ak-pynn
Version: 0.1.8
Summary: A simplistic and efficient pure-python neural network library that allows to build multilayer neural network with ease.
Author: Ankit kohli
Author-email: <contact.ankitkohli@gmail.com>
License: MIT
Keywords: neural network,pure python,ankit_nn,machine learning,ML,deep learning,deepL,MLP,perceptron,ankit kohli,ak_pynn
Classifier: Development Status :: 5 - Production/Stable
Classifier: Topic :: Scientific/Engineering :: Artificial Intelligence
Classifier: Intended Audience :: Science/Research
Classifier: License :: OSI Approved :: MIT License
Classifier: Programming Language :: Python :: 3 :: Only
Classifier: Programming Language :: Python :: 3.0
Classifier: Programming Language :: Python :: 3.4
Classifier: Programming Language :: Python :: 3.5
Classifier: Programming Language :: Python :: 3.6
Classifier: Programming Language :: Python :: 3.7
Classifier: Programming Language :: Python :: 3.8
Classifier: Programming Language :: Python :: 3.9
Classifier: Programming Language :: Python :: 3.10
Classifier: Programming Language :: Python :: 3.11
Classifier: Operating System :: Microsoft :: Windows
Classifier: Operating System :: Unix
Classifier: Operating System :: POSIX :: Linux
Classifier: Operating System :: MacOS :: MacOS X
License-File: LICENCE.md
Requires-Dist: numpy
Requires-Dist: tqdm
Requires-Dist: opt-einsum
Requires-Dist: matplotlib
Requires-Dist: numexpr
Requires-Dist: seaborn
